pyprodj/__init__.py
pyprodj-0.0.1.dist-info/LICENSE
pyprodj-0.0.1.dist-info/METADATA
pyprodj-0.0.1.dist-info/WHEEL
pyprodj-0.0.1.dist-info/top_level.txt
pyprodj-0.0.1.dist-info/RECORD
