Metadata-Version: 2.1
Name: pyprodj
Version: 0.0.1
Summary: Library for interfacing with Pioneer ProDJ Link
Home-page: https://github.com/jackorobot/pyprodj
Author: Jesse Hoogervorst
License: UNKNOWN
Project-URL: Source, https://github.com/jackorobot/pyprodj
Platform: UNKNOWN
Classifier: Programming Language :: Python :: 3
Classifier: License :: OSI Approved :: MIT License
Classifier: Operating System :: OS Independent
